sentry_jira/__init__.py
sentry_jira/forms.py
sentry_jira/jira.py
sentry_jira/models.py
sentry_jira/plugin.py
sentry_jira/__init__.pyc
sentry_jira/forms.pyc
sentry_jira/jira.pyc
sentry_jira/models.pyc
sentry_jira/plugin.pyc
sentry_jira/templates/sentry_jira/create_jira_issue.html
sentry_jira/templates/sentry_jira/plugin_misconfigured.html
sentry_jira/templates/sentry_jira/project_conf_form.html
sentry_jira-0.11.1.dist-info/top_level.txt
sentry_jira-0.11.1.dist-info/entry_points.txt
sentry_jira-0.11.1.dist-info/METADATA
sentry_jira-0.11.1.dist-info/DESCRIPTION.rst
sentry_jira-0.11.1.dist-info/metadata.json
sentry_jira-0.11.1.dist-info/WHEEL
sentry_jira-0.11.1.dist-info/RECORD
