Metadata-Version: 2.0
Name: sentry-jira
Version: 0.11.1
Summary: A Sentry extension which creates JIRA issues from sentry events.
Home-page: http://github.com/thurloat/sentry-jira
Author: Adam Thurlow
Author-email: thurloat@gmail.com
License: BSD
Platform: UNKNOWN
Classifier: Intended Audience :: Developers
Classifier: Intended Audience :: System Administrators
Classifier: Operating System :: OS Independent
Classifier: License :: OSI Approved :: BSD License
Classifier: Programming Language :: Python
Classifier: Framework :: Django
Classifier: Topic :: Software Development
Requires-Dist: sentry (>=7.0.0)
Requires-Dist: BeautifulSoup (>=3.2.1)
Provides-Extra: tests
Requires-Dist: exam; extra == 'tests'
Requires-Dist: flake8 (>=2.0,<2.1); extra == 'tests'
Requires-Dist: responses; extra == 'tests'
